zensols/datdesc/resources/app.conf
zensols/datdesc/resources/default.yml
zensols/datdesc/resources/figure.yml
zensols/datdesc/resources/table.yml
zensols/datdesc/__init__.py
zensols/datdesc/app.py
zensols/datdesc/cli.py
zensols/datdesc/desc.py
zensols/datdesc/dfstash.py
zensols/datdesc/figure.py
zensols/datdesc/hyperparam.py
zensols/datdesc/latex.py
zensols/datdesc/opt.py
zensols/datdesc/optscore.py
zensols/datdesc/plots.py
zensols/datdesc/table.py
zensols_datdesc-1.4.2.dist-info/METADATA
zensols_datdesc-1.4.2.dist-info/WHEEL
zensols_datdesc-1.4.2.dist-info/entry_points.txt
zensols_datdesc-1.4.2.dist-info/licenses/LICENSE.md
zensols_datdesc-1.4.2.dist-info/RECORD
