Metadata-Version: 2.3
Name: zensols_datdesc
Version: 1.4.2
Summary: This API and command line program describes data in tables with metadata and generate LaTeX tables in a `.sty` file from CSV files.
Project-URL: Homepage, https://github.com/plandes/datdesc
Project-URL: Documentation, https://plandes.github.io/datdesc
Project-URL: Repository, https://github.com/plandes/datdesc.git
Project-URL: Issues, https://github.com/plandes/datdesc/issues
Project-URL: Changelog, https://github.com/plandes/datdesc/blob/master/CHANGELOG.md
Author-email: Paul Landes <landes@mailc.net>
License: MIT
Keywords: academia,data,tooling
Requires-Python: <3.15,>=3.11
Requires-Dist: hyperopt~=0.2.7
Requires-Dist: jinja2~=3.1.6
Requires-Dist: matplotlib~=3.10.8
Requires-Dist: numpy==2.4.0
Requires-Dist: pandas~=2.3.3
Requires-Dist: seaborn~=0.13.2
Requires-Dist: tabulate~=0.9.0
Requires-Dist: xlsxwriter==3.0.3
Requires-Dist: zensols-util~=1.16.3
